oneNeuron/__init__.py
oneNeuron/perceptron.py
oneNeuron_kkc11-0.0.3.dist-info/METADATA
oneNeuron_kkc11-0.0.3.dist-info/WHEEL
oneNeuron_kkc11-0.0.3.dist-info/top_level.txt
oneNeuron_kkc11-0.0.3.dist-info/RECORD
